[
    {
      "id": "s001",
      "titre": "Dégustation de vins et fromages",
      "description": "Soirée conviviale de dégustation de vins et fromages dans un cadre intime avec un chef expérimenté.",
      "dateHeure": "2024-06-10T19:00:00Z",
      "lieu": "Le Bistrot Gourmand, Lyon",
      "nbMaxParticipants": 20,
      "organisateur": "fr025",
      "participants": ["fr025", "be026", "pt027"],
      "type": "GASTRO",
      "groupeAge": "ADULTE_MOINS_70",
      "estAnnulee": false
    },
    {
      "id": "s002",
      "titre": "Dîner culturel et soirée jazz",
      "description": "Un dîner gastronomique suivi d'une soirée jazz dans un restaurant à l'ambiance unique.",
      "dateHeure": "2024-06-12T20:00:00Z",
      "lieu": "Jazz Bistro, Londres",
      "nbMaxParticipants": 15,
      "organisateur": "uk028",
      "participants": ["uk028", "fr025", "ch029"],
      "type": "GASTRO",
      "groupeAge": "ADULTE_MOINS_70",
      "estAnnulee": false
    },
    {
      "id": "s003",
      "titre": "Soirée culturelle au musée",
      "description": "Visite guidée du musée suivi d'un dîner avec une discussion sur l'art contemporain.",
      "dateHeure": "2024-06-15T18:30:00Z",
      "lieu": "Musée d'Art Contemporain, Bruxelles",
      "nbMaxParticipants": 30,
      "organisateur": "be026",
      "participants": ["be026", "pt027", "fr025"],
      "type": "CULTURE",
      "groupeAge": "ADULTE_MOINS_70",
      "estAnnulee": false
    },
    {
      "id": "s004",
      "titre": "Dîner gastronomique portugais",
      "description": "Un dîner gastronomique traditionnel portugais dans un restaurant avec une vue splendide.",
      "dateHeure": "2024-06-18T19:30:00Z",
      "lieu": "Restaurante Lisboa, Lisbonne",
      "nbMaxParticipants": 25,
      "organisateur": "pt027",
      "participants": ["pt027", "fr025", "ch029"],
      "type": "GASTRO",
      "groupeAge": "ADULTE_MOINS_70",
      "estAnnulee": false
    },
    {
      "id": "s005",
      "titre": "Soirée fondue suisse",
      "description": "Dégustation de fondue suisse avec une sélection de fromages et de vins locaux dans une ambiance chaleureuse.",
      "dateHeure": "2024-06-20T18:00:00Z",
      "lieu": "Le Chalet de Montagne, Zurich",
      "nbMaxParticipants": 18,
      "organisateur": "ch029",
      "participants": ["ch029", "uk028", "be026"],
      "type": "GASTRO",
      "groupeAge": "ADULTE_MOINS_70",
      "estAnnulee": false
    },
    {
          "id": "s006",
          "titre": "Concert de musique classique",
          "description": "Un concert de musique classique en plein air avec un orchestre de renommée mondiale.",
          "dateHeure": "2024-06-25T20:00:00Z",
          "lieu": "Parc des Expositions, Paris",
          "nbMaxParticipants": 200,
          "organisateur": "fr025",
          "participants": ["fr025", "be026", "ch029"],
          "type": "CULTURE",
          "groupeAge": "ADULTE_MOINS_70",
          "estAnnulee": false
        },
        {
          "id": "s007",
          "titre": "Randonnée dans les montagnes des Alpes",
          "description": "Une randonnée guidée dans les Alpes, adaptée à tous les niveaux avec des vues spectaculaires.",
          "dateHeure": "2024-07-05T08:00:00Z",
          "lieu": "Chamonix, Alpes",
          "nbMaxParticipants": 15,
          "organisateur": "fr025",
          "participants": ["fr025", "ch029"],
          "type": "SPORT",
          "groupeAge": "ADULTE_MOINS_70",
          "estAnnulee": false
        },
        {
          "id": "s008",
          "titre": "Dégustation de chocolat et café",
          "description": "Dégustation de chocolats fins et de cafés exotiques dans un cadre cosy et agréable.",
          "dateHeure": "2024-07-10T17:30:00Z",
          "lieu": "Café Gourmand, Bruxelles",
          "nbMaxParticipants": 25,
          "organisateur": "be026",
          "participants": ["be026", "pt027", "ch029"],
          "type": "GASTRO",
          "groupeAge": "ADULTE_MOINS_70",
          "estAnnulee": false
        },
        {
          "id": "s009",
          "titre": "Séance de yoga au lever du soleil",
          "description": "Séance de yoga en plein air au lever du soleil avec un instructeur expérimenté.",
          "dateHeure": "2024-07-12T06:00:00Z",
          "lieu": "Plage de Nice, Nice",
          "nbMaxParticipants": 30,
          "organisateur": "fr025",
          "participants": ["fr025", "pt027"],
          "type": "SPORT",
          "groupeAge": "ADULTE_MOINS_70",
          "estAnnulee": false
        },
        {
          "id": "s010",
          "titre": "Visite guidée du château de Versailles",
          "description": "Visite guidée du château de Versailles, avec une découverte approfondie de l'histoire et des jardins.",
          "dateHeure": "2024-07-15T10:00:00Z",
          "lieu": "Château de Versailles, Versailles",
          "nbMaxParticipants": 40,
          "organisateur": "fr025",
          "participants": ["fr025", "ch029", "be026"],
          "type": "CULTURE",
          "groupeAge": "ADULTE_MOINS_70",
          "estAnnulee": false
        },
        
            {
              "id": "s011",
              "titre": "Atelier de peinture au vin",
              "description": "Un atelier créatif où vous pourrez peindre tout en dégustant du vin, un moment artistique et convivial.",
              "dateHeure": "2024-07-18T15:00:00Z",
              "lieu": "Galerie d'Art, Lyon",
              "nbMaxParticipants": 20,
              "organisateur": "fr025",
              "participants": ["fr025", "be026", "ch029"],
              "type": "CULTURE",
              "groupeAge": "ADULTE_MOINS_70",
              "estAnnulee": false
            },
            {
              "id": "s012",
              "titre": "Visite en vélo de la ville",
              "description": "Découvrez la ville de Lyon à vélo, en passant par ses monuments historiques et ses quartiers pittoresques.",
              "dateHeure": "2024-07-20T09:00:00Z",
              "lieu": "Centre-ville de Lyon",
              "nbMaxParticipants": 25,
              "organisateur": "fr025",
              "participants": ["fr025", "be026", "ch029", "pt027"],
              "type": "CULTURE",
              "groupeAge": "ADULTE_MOINS_70",
              "estAnnulee": false
            },
            {
              "id": "s013",
              "titre": "Escape Game sur le thème de l'Histoire",
              "description": "Participez à un escape game immersif basé sur des événements historiques majeurs. Travaillez en équipe pour résoudre les énigmes.",
              "dateHeure": "2024-07-25T14:00:00Z",
              "lieu": "Escape Room, Marseille",
              "nbMaxParticipants": 12,
              "organisateur": "fr025",
              "participants": ["fr025", "be026"],
              "type": "JEU",
              "groupeAge": "ADULTE_MOINS_70",
              "estAnnulee": false
            },
            {
              "id": "s014",
              "titre": "Soirée de danse salsa",
              "description": "Venez apprendre les pas de salsa et vous amuser lors d'une soirée dansante avec un DJ en direct.",
              "dateHeure": "2024-07-28T21:00:00Z",
              "lieu": "Club Salsa, Paris",
              "nbMaxParticipants": 100,
              "organisateur": "fr025",
              "participants": ["fr025", "ch029", "pt027"],
              "type": "SOCIAL",
              "groupeAge": "ADULTE_MOINS_70",
              "estAnnulee": false
            },
            {
              "id": "s015",
              "titre": "Visite gastronomique des marchés de Provence",
              "description": "Explorez les marchés locaux de Provence, dégustez des produits frais et apprenez à cuisiner des plats régionaux.",
              "dateHeure": "2024-08-02T08:00:00Z",
              "lieu": "Provence, Marseille",
              "nbMaxParticipants": 15,
              "organisateur": "fr025",
              "participants": ["fr025", "ch029", "be026"],
              "type": "GASTRO",
              "groupeAge": "ADULTE_MOINS_70",
              "estAnnulee": false
            }
          ]
          
        